{"generatedAt":1693967727107,"generateTime":88,"contents":[{"_path":"/blog/hello","_dir":"blog","_draft":false,"_partial":false,"_locale":"","title":"Hello!","description":"","body":{"type":"root","children":[{"type":"element","tag":"h1","props":{"id":"hello"},"children":[{"type":"text","value":"Hello!"}]},{"type":"element","tag":"h2","props":{"id":"this-is-less-cool"},"children":[{"type":"text","value":"This is less cool"}]}],"toc":{"title":"","searchDepth":2,"depth":2,"links":[{"id":"this-is-less-cool","depth":2,"text":"This is less cool"}]}},"_type":"markdown","_id":"content:blog:hello.md","_source":"content","_file":"blog/hello.md","_extension":"md"},{"_path":"/blog","_dir":"","_draft":false,"_partial":false,"_locale":"","title":"","description":"i have no idea","body":{"type":"root","children":[{"type":"element","tag":"p","props":{},"children":[{"type":"text","value":"i have no idea"}]}],"toc":{"title":"","searchDepth":2,"depth":2,"links":[]}},"_type":"markdown","_id":"content:blog:index.md","_source":"content","_file":"blog/index.md","_extension":"md"}],"navigation":[{"title":"","_path":"/blog","children":[{"title":"Hello!","_path":"/blog/hello"},{"title":"","_path":"/blog"}]}]}